f451_comms/__init__.py
f451_comms/__main__.py
f451_comms/comms.py
f451_comms/config.ini.example
f451_comms/constants.py
f451_comms/entity.py
f451_comms/exceptions.py
f451_comms/processor.py
f451_comms/providers/__init__.py
f451_comms/providers/email.py
f451_comms/providers/mailgun.py
f451_comms/providers/provider.py
f451_comms/providers/slack.py
f451_comms/providers/sms.py
f451_comms/providers/twilio.py
f451_comms/providers/twitter.py
f451_comms/py.typed
f451_comms/secrets.ini.example
f451_comms/utils.py
f451_comms-0.1.1.dist-info/entry_points.txt
f451_comms-0.1.1.dist-info/LICENSE.rst
f451_comms-0.1.1.dist-info/WHEEL
f451_comms-0.1.1.dist-info/METADATA
f451_comms-0.1.1.dist-info/RECORD
