Metadata-Version: 2.1
Name: f451-comms
Version: 0.1.1
Summary: f451 Communications Module
Home-page: https://github.com/mlanser/f451-comms
License: MIT
Author: Martin Lanser
Author-email: martinlanser@gmail.com
Requires-Python: >=3.8,<4.0
Classifier: Development Status :: 1 - Planning
Classifier: License :: OSI Approved :: MIT License
Classifier: Programming Language :: Python :: 3
Classifier: Programming Language :: Python :: 3.10
Classifier: Programming Language :: Python :: 3.8
Classifier: Programming Language :: Python :: 3.9
Requires-Dist: Faker (>=13.7.0,<14.0.0)
Requires-Dist: argparse (>=1.4.0,<2.0.0)
Requires-Dist: konsole (>=0.6.0,<0.7.0)
Requires-Dist: nox (>=2022.1.7,<2023.0.0)
Requires-Dist: rich (>=12.2.0,<13.0.0)
Requires-Dist: sendgrid (>=6.9.7,<7.0.0)
Requires-Dist: slack-bolt (>=1.11.1,<2.0.0)
Requires-Dist: tweepy (>=4.9.0,<5.0.0)
Requires-Dist: twilio (>=7.9.0,<8.0.0)
Requires-Dist: types-requests (>=2.27.16,<3.0.0)
Project-URL: Changelog, https://github.com/mlanser/f451-comms/releases
Project-URL: Documentation, https://f451-comms.readthedocs.io
Project-URL: Repository, https://github.com/mlanser/f451-comms
